MANIFEST.in
README.md
requirements.txt
setup.py
medipack/__init__.py
medipack/main.py
medipack.egg-info/PKG-INFO
medipack.egg-info/SOURCES.txt
medipack.egg-info/dependency_links.txt
medipack.egg-info/entry_points.txt
medipack.egg-info/requires.txt
medipack.egg-info/top_level.txt
medipack/dependencies/__init__.py
medipack/dependencies/dependencies.py
medipack/dependencies/dependency.py
medipack/lib/__init__.py
medipack/lib/args.py
medipack/lib/meditor.py
medipack/lib/srbColour.py
medipack/lib/time.py
medipack/lib/util.py
test/__init__.py