Metadata-Version: 2.1
Name: medipack
Version: 2.0.1
Summary: A command line tool for media editing
Home-page: http://github.com/srbcheema1/medipack
Author: Sarbjit Singh
Author-email: srbcheema1@gmail.com
License: MIT License
Platform: UNKNOWN
Classifier: Operating System :: POSIX :: Linux
Classifier: License :: OSI Approved :: MIT License
Classifier: Programming Language :: Python :: 3.5
